Workbook

Sheet Portada
B2: EVALUACIÓN DE MADUREZ DCAM
B3: Adaptado al proceso de venta de ganado · Sistema Subastar
B4: Basado en el Data Management Capability Assessment Model (DCAM) – EDM Council
B7: Organización evaluada | C7: Subastar EC
B8: Responsable del levantamiento | C8: Bryan Sanches
B9: Fecha de inicio | C9: 46191
B10: Fecha de cierre | C10: 46224
B11: Versión del documento | C11: 1.0
B14: Escala de madurez DCAM (1–6)
B15: 1 – No iniciado | C15: Las capacidades no existen o son completamente ad hoc. No hay proceso, política ni responsable definido.
B16: 2 – Conceptual | C16: Existe conciencia del tema y hay conversaciones iniciales. Se planifica pero nada está formalizado ni aprobado.
B17: 3 – En desarrollo | C17: Se han identificado responsables, se aprobó financiamiento inicial y los procedimientos están en construcción.
B18: 4 – Definido | C18: Los procesos están documentados, roles asignados y las políticas aprobadas. Implementación consistente en marcha.
B19: 5 – Logrado | C19: La capacidad está completamente operativa, se mide con KPIs y se mejora continuamente con base en resultados.
B20: 6 – Mejorado | C20: La capacidad está integrada en la cultura organizacional. Se benchmarka con la industria y lidera buenas prácticas.
B22: Cómo usar este archivo
B23: 1. Complete una hoja por cada Componente DCAM (C1 a C8) asignando puntaje 1–6 a cada capacidad.
B24: 2. Use el desplegable de la columna 'Puntaje' — no escriba el número directamente.
B25: 3. Documente la evidencia concreta que justifica el puntaje en la columna 'Evidencia observada'.
B26: 4. Identifique la brecha principal y la acción de mejora recomendada para cada capacidad.
B27: 5. La hoja 'Diagnóstico y Radar' se actualiza automáticamente con los puntajes ingresados.

Sheet C1 – Estrategia de gestión 
B1: COMPONENTE 1 · ESTRATEGIA DE GESTIÓN DE DATOS
B2: Define la visión, objetivos y hoja de ruta del programa de datos alineado al negocio.
B3: Escala: 1 No iniciado · 2 Conceptual · 3 En desarrollo · 4 Definido · 5 Logrado · 6 Mejorado
B4: Capacidad | C4: Descripción | D4: Puntaje (1–6) | E4: Preguntas de evidencia | F4: Evidencia observada (documentar hallazgo) | G4: Acción de mejora recomendada
B5: Visión y objetivos de datos | C5: Existe una visión documentada sobre cómo los datos apoyan los objetivos del negocio. | D5: 4 | E5: 1. ¿Existe un documento de estrategia de datos aprobado por la gerencia? | F5: De acuerdo con el Gerente de Gobernanza, sí existen políticas y procedimientos documentados ("normativa de planta de la empresa") sobre cómo registrar, actualizar o eliminar datos . Sin embargo, la estrategia profunda, informática y las auditorías de datos no se manejan localmente, sino que están centralizadas desde la gerencia general e informática en Colombia .
E6: 2. ¿Los objetivos de datos están alineados con la estrategia del negocio ganadero? | F6: Sí, están totalmente alineados. La recolección de datos operativos (registro de clientes, pre-ingreso de volúmenes y lotes) tiene el objetivo directo de hacer "pre-mercadeo" para atraer a los compradores adecuados según la categoría de ganado. Todos los datos registrados en el "Menú SIS" y el módulo de pesaje sustentan el modelo de negocio, permitiendo la facturación y el cobro de comisiones.
E7: 3. ¿Se comunica la estrategia de datos a todos los niveles de la organización? | F7: A nivel operativo sí se aplican las normativas de datos. Se evidencia que los empleados conocen sus responsabilidades de registro y los límites de sus permisos; el sistema tiene accesos diferenciados por roles (operativo, comercial, facturación) , y el personal operativo tiene claro que una vez ingresado un lote a báscula, los datos son inmodificables
B9: Hoja de ruta del programa | C9: Existe un plan de acción con iniciativas, plazos y responsables definidos. | D9: 4 | E9: 1. ¿Hay una hoja de ruta de datos con iniciativas priorizadas? | F9: No se evidencia en las entrevistas la existencia de una hoja de ruta de datos local formalizada con fechas o presupuestos definidos. Cuando se le consultó al Gerente sobre la visión de gobernanza a mediano plazo, indicó que siempre están dispuestos a realizar mejoras, pero señaló que actualmente la empresa "no tiene que querer un poco mejorar en esto" . Mencionó que ha habido integraciones recientes con Inteligencia Artificial, pero aclaró que "no con el tema de interferencia de datos" . Dado que el sistema ("Menú SIS") y su desarrollo pertenecen a la sede en Colombia , cualquier hoja de ruta tecnológica se rige desde la casa matriz y no como un plan de acción local independiente.
E10: 2. ¿Las iniciativas de datos tienen fechas, responsables y presupuesto asignado? | F10: No existe evidencia de que a nivel local (Subastar Ecuador) se cuente con iniciativas de datos estructuradas que incluyan fechas, responsables locales o un presupuesto asignado.
E11: 3. ¿Se revisa y actualiza la hoja de ruta periódicamente? | F11: A nivel local no existe una revisión ni actualización periódica de una hoja de ruta de datos.
B13: Métricas de valor del dato | C13: Se miden los beneficios generados por el programa de datos. | D13: 5 | E13: 1. ¿Existen KPIs para medir el impacto de la gestión de datos en el negocio? | F13: Sí. Se cuenta con un tablero de informes en el sistema y se maneja un archivo de Excel detallado con indicadores comerciales que incluyen: número de vacas ingresadas, cantidad de compradores, porcentajes de venta y procedencia
E14: 2. ¿Se reporta el valor del programa de datos a la gerencia? | F14: Sí, el Gerente confirmó que evalúa estos datos con alta frecuencia: "Semana a semana se hace un chequeo de indicadores comerciales" para observar autosubastas, proveedores y comercialización . Estos datos alimentan directamente la toma de decisiones gerenciales y comerciales
E15: 3. ¿Se vincula la calidad de datos con resultados operativos (precios, trazabilidad)? | F15: Totalmente. La calidad y exactitud del dato es tratada como algo crítico para la operación. El Director Operativo menciona que el error más grave que puede existir es que el número de lote físico pintado en el animal no coincida con el registrado en el sistema, ya que esto afecta directamente quién cobra y quién paga . Así mismo, el sistema asocia de forma estricta el registro inicial de la guía SIFAE para respaldar el origen y permitir la posterior salida legal de los animales comprado
B18: Puntaje promedio del componente | D18: =IFERROR(AVERAGE(D5,D9,D13),"") -> 4.3333333

Sheet C2 – Programa y financiamie
B1: COMPONENTE 2 · PROGRAMA Y FINANCIAMIENTO
B2: Justifica, organiza y financia el programa de gestión de datos de forma sostenida.
B3: Escala: 1 No iniciado · 2 Conceptual · 3 En desarrollo · 4 Definido · 5 Logrado · 6 Mejorado
B4: Capacidad | C4: Descripción | D4: Puntaje (1–6) | E4: Preguntas de evidencia | F4: Evidencia observada (documentar hallazgo) | G4: Acción de mejora recomendada
B5: Caso de negocio del programa | C5: Existe un caso de negocio que justifica la inversión en gestión de datos. | D5: 1 | E5: 1. ¿Se ha elaborado un caso de negocio para el programa de datos? | F5: No a nivel local. No existe evidencia de que Subastar Ecuador haya elaborado un caso de negocio enfocado en la gestión de datos. El Gerente de Gobernanza aclaró explícitamente que todo el manejo de informática, auditorías y gobernanza profunda se maneja directamente desde la casa matriz en Colombia . Además, señaló que a nivel local no están buscando mejoras relacionadas con la "interferencia de datos" | G5: visibilñizar el negocio
E6: 2. ¿La gerencia ha aprobado formalmente el programa y su presupuesto? | F6: No. Al no existir un programa de datos local autónomo, la gerencia local no aprueba presupuestos para este fin. Cualquier inversión en el desarrollo o mejora del sistema (como integraciones recientes de Inteligencia Artificial) se aprueba y gestiona desde la Gerencia General en Colombia
E7: 3. ¿El caso de negocio considera los riesgos de NO gestionar los datos? | F7: Aunque no existe un documento formal de caso de negocio, a nivel operativo sí existe una alta conciencia del riesgo de un mal manejo de los datos críticos.
B9: Estructura del programa | C9: El programa tiene una estructura organizacional con roles y responsabilidades claras. | D9: 5 | E9: 1. ¿Existe un comité o equipo responsable del programa de datos? | F9: Las auditorías y el control estricto del sistema informático ("Menú SIS") recaen en el departamento de Informática ubicado en Colombia
E10: 2. ¿Los roles de gestión de datos están definidos en organigramas o descripciones de cargo? | F10: No existen títulos formales de "gobernanza de datos", pero las responsabilidades operativas de ingreso y cuidado de datos sí están claramente definidas en los cargos. Se estableció que el Director Operativo es el responsable formal de garantizar que los datos estén correctos y actualizados . Adicionalmente, el acceso a la información está estrictamente segmentado por roles; por ejemplo, la analista de facturación tiene acceso exclusivo a ese módulo, sin que otras áreas puedan modificarlo
E11: 3. ¿El programa tiene un sponsor ejecutivo identificado? | F11: No a nivel local. Cualquier patrocinio tecnológico y estratégico recae en la alta dirección (Gerencia General) en Colombia, no en la sucursal ecuatoriana
B13: Financiamiento sostenible | C13: El programa cuenta con presupuesto recurrente, no solo proyecto a proyecto. | D13: 1 | E13: 1. ¿El presupuesto de gestión de datos es recurrente (no solo puntual)? | F13: No existe evidencia de un presupuesto asignado, ni recurrente ni puntual, para la gestión de datos en la sucursal de Ecuador.
E14: 2. ¿Existe un modelo de costos para las actividades de datos? | F14: Subastar Ecuador funciona operativamente como un ente comercial y logístico , adoptando el modelo de negocio y los sistemas ("Menú SIS") creados e implementados por Colombia . Por lo tanto, no manejan un modelo de costos local estructurado para el mantenimiento, actualización o gobernanza de los datos.
E15: 3. ¿El financiamiento cubre herramientas, personas y capacitación? | F15: En las entrevistas no se menciona ningún tipo de financiamiento local destinado a contratar personal especializado en gobernanza de datos o a capacitar al personal en este ámbito específico; de hecho, el Gerente señala que actualmente la empresa a nivel local no tiene enfoques de mejora en el tema de la "interferencia de datos"
B18: Puntaje promedio del componente | D18: =IFERROR(AVERAGE(D5,D9,D13),"") -> 2.3333333

Sheet C3 – Gobernanza de datos
B1: COMPONENTE 3 · GOBERNANZA DE DATOS
B2: Establece políticas, roles, responsabilidades y mecanismos de decisión sobre los datos.
B3: Escala: 1 No iniciado · 2 Conceptual · 3 En desarrollo · 4 Definido · 5 Logrado · 6 Mejorado
B4: Capacidad | C4: Descripción | D4: Puntaje (1–6) | E4: Preguntas de evidencia | F4: Evidencia observada (documentar hallazgo) | G4: Acción de mejora recomendada
B5: Políticas y estándares | C5: Existen políticas formales que regulan cómo se gestionan, usan y protegen los datos. | D5: 2 | E5: 1. ¿Existen políticas documentadas de calidad, retención y acceso a datos? | F5: El Gerente de Gobernanza confirma que existe una "normativa de planta de la empresa" documentada que dicta cómo se debe registrar, actualizar o eliminar la información. Adicionalmente, el acceso a los datos está estrictamente controlado por políticas del sistema: no todos tienen los mismos permisos, sino que el acceso a cada módulo depende del rango y tipo de puesto del usuario
E6: 2. ¿Las políticas de datos están aprobadas y comunicadas a los usuarios del sistema Subastar? | F6: Sí, operativamente. Aunque la directriz viene de Colombia, los usuarios locales conocen perfectamente sus restricciones. Por ejemplo, el Director Operativo sabe que él es el único que opera el "Módulo de pesaje" y que, una vez ingresado un lote, la política del sistema impide su modificación . Asimismo, la responsable financiera tiene claro que el módulo de facturación es de acceso exclusivo para su cargo
E7: 3. ¿Se revisan y actualizan las políticas periódicamente? | F7: No a nivel local. La revisión de políticas profundas, auditorías y cambios en el sistema se gestionan directamente desde la Gerencia General e Informática en Colombia, no existe evidencia de una revisión periódica autónoma en la sede de Ecuador
B9: Roles de gobernanza (Data Owners/Stewards) | C9: Están definidos y asignados los responsables de cada dominio de datos. | D9: 2 | E9: 1. ¿Están identificados los Data Owners para cada entidad clave (Animal, Comprador, Transacción)? | F9: No bajo títulos formales de "Data Owners", pero sí en la práctica operativa. El "Módulo de pesaje" (datos de animales y lotes) es propiedad exclusiva del Director Operativo, el registro de clientes (compradores/vendedores) recae en el Área Comercial y Operativa, y las transacciones/liquidaciones son de propiedad exclusiva del Área de Facturación.
E10: 2. ¿Existen Data Stewards responsables de la calidad operativa de los datos? | F10: El Gerente designó formalmente al Director Operativo como el responsable de garantizar que los datos estén correctos y actualizados . Él actúa como el "Data Steward" principal en campo, tomando la decisión crítica de verificar que el lote físico marcado en el animal coincida exactamente con el lote ingresado en el sistema, considerando cualquier discrepancia como un "error grave
E11: 3. ¿Los roles de gobernanza están documentados con sus responsabilidades? | F11: Están documentados dentro de las descripciones y perfiles de cargo ("dependiendo del rango y el tipo de puesto" ), pero están enfocados a la operatividad del sistema "Menú SIS", no como un programa independiente de gobernanza de datos.
B13: Glosario y definiciones | C13: Existe un vocabulario común y acordado para los términos de negocio clave. | D13: 2 | E13: 1. ¿Existe un glosario de términos de negocio (Lote, Arete, Guía, Puja base)? | F13: No existe evidencia de un documento formal tipo "glosario"pero existe una estandarización estricta de los términos impuesta por el propio sistema informático. Conceptos como "Autosubasta" , "Liquidación de compra/venta" , "Guía de Movilización (SIFAE)" y "Lote" significan exactamente lo mismo para todos los actores porque los campos del "Menú SIS" así lo exigen.
E14: 2. ¿El glosario es accesible a todos los usuarios del sistema? | F14: No. Al carecer de un documento formal de glosario de datos, estas prácticas no se aplican
E15: 3. ¿Se gestiona el glosario de forma centralizada y con control de versiones? | F15: No. Al carecer de un documento formal de glosario de datos, estas prácticas no se aplican
B17: Comité de gobernanza | C17: Existe un foro formal para tomar decisiones sobre políticas y estándares de datos. | D17: 1 | E17: 1. ¿Existe un comité o instancia formal para resolver conflictos de datos? | F17: No a nivel local. El Gerente de Gobernanza es claro al indicar que cualquier tema relacionado con auditorías informáticas o resolución de problemas profundos de datos no se maneja en Ecuador, sino que recae directamente en la Gerencia General junto con el departamento de Informática en Colombia
E18: 2. ¿Las decisiones sobre datos se documentan y comunican? | F18: Al no existir un comité de gobernanza de datos en Subastar Ecuador, no se generan actas, reuniones formales ni comunicaciones de decisiones estratégicas de datos a nivel local
E19: 3. ¿El comité se reúne con frecuencia definida y tiene actas? | F19: No. Al carecer de un comité, estas prácticas no se aplican
B22: Puntaje promedio del componente | D22: =IFERROR(AVERAGE(D5,D9,D13,D17),"") -> 1.75

Sheet C4 – Arquitectura de datos
B1: COMPONENTE 4 · ARQUITECTURA DE DATOS
B2: Define la estructura, flujos e integración de datos entre sistemas y procesos.
B3: Escala: 1 No iniciado · 2 Conceptual · 3 En desarrollo · 4 Definido · 5 Logrado · 6 Mejorado
B4: Capacidad | C4: Descripción | D4: Puntaje (1–6) | E4: Preguntas de evidencia | F4: Evidencia observada (documentar hallazgo) | G4: Acción de mejora recomendada
B5: Modelo de datos del negocio | C5: Existe un modelo de datos que refleja las entidades del proceso de venta de ganado. | D5: 2 | E5: 1. ¿Existe un modelo entidad-relación (ER) documentado del sistema Subastar? | F5: No a nivel local. La arquitectura del software ("Menú SIS", Módulo de pesaje, etc.) fue creada y es administrada íntegramente por la casa matriz en Colombia. No hay evidencia de que la sucursal en Ecuador posea documentación técnica sobre la estructura de la base de datos.
E6: 2. ¿El modelo de datos está actualizado y refleja el estado actual de la base de datos? | F6: No para el equipo de Ecuador. Subastar Ecuador no cuenta con un departamento de TI local (informática se maneja desde Colombia)
E7: 3. ¿El modelo es accesible para el equipo de negocio y TI? | F7: El equipo de negocio local (Gerente, Director Comercial, Operador) interactúa únicamente con la interfaz operativa del sistema (front-end) y no tiene acceso a los modelos de bases de datos o diagramas ER
B9: Mapa de flujos de datos | C9: Se documenta cómo fluyen los datos entre sistemas, procesos y actores. | D9: 3 | E9: 1. ¿Existe un mapa de flujo de datos desde el registro del animal hasta la transacción? | F9: No hay evidencia de un documento técnico local, aunque el flujo es conocido operativamente. El personal conoce a la perfección la ruta de los datos (Página web para clientes -> Módulo de pesaje -> Display -> Menú SIS -> SIESA/Génesis para facturación) , pero no se menciona la existencia de un mapa formal de arquitectura documentado en la sede local.
E10: 2. ¿Se documentan las integraciones entre Subastar, ERP, AGROCALIDAD y otros sistemas? auditoria | F10: Al no haber departamento TI local, no hay documentación técnica a la mano, pero operativamente se aclaró lo siguiente sobre las integraciones: Integración Contable (Sí existe): El Menú SIS exporta la información al sistema ERP "SIESA/Génesis", el cual se vincula y valida datos automáticamente con el SRI . Integración con AGROCALIDAD (No existe): Se confirmó explícitamente que el sistema gubernamental SIFAE es "muy independiente a nuestro programa" . No existe integración entre ambos; el personal de Subastar simplemente entra al portal web externo de SIFAE para verificar visualmente los códigos de las guías de movilización físicas que entregan los ganaderos
E11: 3. ¿Se identifican y documentan los puntos de entrada manual de datos? | F11: Sí, en la práctica operativa están estrictamente identificados. Se han definido tres puntos de entrada principales y separados: el formulario web de inscripción para clientes nuevos, el "Módulo de pesaje" operado exclusivamente por el Director Operativo, y el "Módulo Display" para registrar el avance de la puja.
B13: Gestión de datos maestros y de referencia | C13: Los datos compartidos (razas, provincias, usuarios) se gestionan de forma centralizada. | D13: 1 | E13: 1. ¿Existe una fuente única de verdad para datos maestros como razas, provincias, compradores? | F13: Sí. El "Menú SIS" funciona como el sistema centralizado y la única fuente de verdad. El operador confirma que toda la información recolectada desde otras plataformas "se almacena en el SIS. El SIS es nuestro módulo principal donde toda la información recolectada se almacena"
E14: 2. ¿Los datos de referencia se sincronizan entre todos los módulos del sistema? | F14: Sí, están sincronizados. El módulo de pesaje y el módulo display no almacenan información permanentemente de forma aislada, sino que envían los registros de forma automática al sistema central SIS . Del mismo modo, un cliente registrado en la página web se refleja directamente en el módulo de clientes del SIS
E15: 3. ¿Se controlan los cambios en los datos de referencia con aprobación y versión? | F15: Sí, a través de bloqueos estrictos del sistema (Hard-coded). Más que un flujo de aprobación de versiones manual, el control de cambios está automatizado por restricciones del software. Una vez que un lote es ingresado en la báscula, o una vez que el animal es facturado, el sistema bloquea los datos y ya no permite su edición o modificación local
B18: Puntaje promedio del componente | D18: =IFERROR(AVERAGE(D5,D9,D13),"") -> 2

Sheet C5 – Calidad de datos
B1: COMPONENTE 5 · CALIDAD DE DATOS
B2: Asegura que los datos sean exactos, completos, consistentes, oportunos y confiables.
B3: Escala: 1 No iniciado · 2 Conceptual · 3 En desarrollo · 4 Definido · 5 Logrado · 6 Mejorado
B4: Capacidad | C4: Descripción | D4: Puntaje (1–6) | E4: Preguntas de evidencia | F4: Evidencia observada (documentar hallazgo) | G4: Acción de mejora recomendada
B5: Reglas y validaciones de calidad | C5: Existen reglas activas que validan la calidad de los datos al momento del ingreso. | D5: 5 | E5: 1. ¿El sistema Subastar tiene validaciones activas para campos obligatorios?
E6: 2. ¿Existen reglas que detecten duplicados de animales o compradores?
E7: 3. ¿Se validan formatos como números de arete, cédulas o fechas?
B9: Medición y monitoreo de calidad | C9: Se mide regularmente la calidad de los datos con indicadores definidos. | D9: 1 | E9: 1. ¿Se mide la completitud de los campos críticos (arete, peso, estado sanitario)?
E10: 2. ¿Existe un reporte periódico de calidad de datos para los responsables?
E11: 3. ¿Se mide la consistencia de datos entre módulos del sistema Subastar?
B13: Proceso de corrección de errores | C13: Existe un proceso definido para reportar y corregir problemas de calidad. | D13: 1 | E13: 1. ¿Existe un canal formal para reportar errores de datos al área responsable?
E14: 2. ¿Se documenta quién corrigió un dato, cuándo y por qué razón?
E15: 3. ¿Los errores corregidos se analizan para prevenir recurrencia?
B17: Perfilado y análisis de datos | C17: Se realizan análisis periódicos del estado de los datos en la base de datos. | D17: 1 | E17: 1. ¿Se realiza perfilado de datos (análisis de nulos, duplicados, rangos) periódicamente?
E18: 2. ¿Los resultados del perfilado se comparten con Data Owners y Stewards?
E19: 3. ¿Se priorizan las correcciones según impacto en el proceso de subasta?
B22: Puntaje promedio del componente | D22: =IFERROR(AVERAGE(D5,D9,D13,D17),"") -> 2

Sheet C6 – Control y riesgo de da
B1: COMPONENTE 6 · CONTROL Y RIESGO DE DATOS
B2: Identifica, mitiga y monitorea los riesgos asociados a seguridad, privacidad y uso de datos.
B3: Escala: 1 No iniciado · 2 Conceptual · 3 En desarrollo · 4 Definido · 5 Logrado · 6 Mejorado
B4: Capacidad | C4: Descripción | D4: Puntaje (1–6) | E4: Preguntas de evidencia | F4: Evidencia observada (documentar hallazgo) | G4: Acción de mejora recomendada
B5: Clasificación y seguridad de datos | C5: Los datos están clasificados por sensibilidad y tienen controles de protección adecuados. | D5: 1 | E5: 1. ¿Los datos del sistema Subastar están clasificados (Público, Interno, Confidencial, Restringido)?
E6: 2. ¿Los datos sensibles de compradores y vendedores tienen controles especiales de acceso?
E7: 3. ¿Se aplica cifrado a datos en tránsito y en reposo para información sensible?
B9: Control de acceso y perfiles | C9: El acceso a los datos está controlado según el rol y necesidad de cada usuario. | D9: 2 | E9: 1. ¿Existen perfiles de usuario diferenciados (solo lectura, edición, administración)?
E10: 2. ¿El acceso al sistema Subastar se revisa y actualiza cuando cambian los roles?
E11: 3. ¿Se registra un log de auditoría de quién accedió y modificó cada registro?
B13: Cumplimiento normativo (LOPDP / AGROCALIDAD) | C13: El manejo de datos cumple con las regulaciones aplicables en Ecuador. | D13: 1 | E13: 1. ¿La empresa conoce y aplica las obligaciones de la LOPDP para datos personales?
E14: 2. ¿Existe un registro de actividades de tratamiento de datos personales?
E15: 3. ¿Los datos de trazabilidad animal cumplen con los requisitos de AGROCALIDAD?
B17: Gestión de incidentes de datos | C17: Existe un proceso para detectar, responder y reportar incidentes de datos. | D17: 1 | E17: 1. ¿Existe un proceso documentado para responder a incidentes de pérdida o filtración de datos?
E18: 2. ¿Los incidentes de datos se reportan a la gerencia y a los organismos correspondientes?
E19: 3. ¿Se realizan respaldos periódicos y se prueban las restauraciones?
B22: Puntaje promedio del componente | D22: =IFERROR(AVERAGE(D5,D9,D13,D17),"") -> 1.25

Sheet C7 – Metadatos
B1: COMPONENTE 7 · METADATOS
B2: Documenta el contexto, linaje, significado y características técnicas de los datos.
B3: Escala: 1 No iniciado · 2 Conceptual · 3 En desarrollo · 4 Definido · 5 Logrado · 6 Mejorado
B4: Capacidad | C4: Descripción | D4: Puntaje (1–6) | E4: Preguntas de evidencia | F4: Evidencia observada (documentar hallazgo) | G4: Acción de mejora recomendada
B5: Diccionario de datos | C5: Existe documentación de los campos, tipos y significados de los datos del sistema. | D5: 1 | E5: 1. ¿Existe un diccionario de datos del sistema Subastar con descripción de cada campo?
E6: 2. ¿El diccionario de datos está actualizado con la versión actual de la base de datos?
E7: 3. ¿El diccionario es accesible tanto para el equipo de negocio como para TI?
B9: Linaje de datos | C9: Se documenta el origen y transformaciones que sufre cada dato a lo largo del proceso. | D9: 1 | E9: 1. ¿Se documenta de dónde viene cada dato (AGROCALIDAD, báscula, formulario manual)?
E10: 2. ¿Se registran las transformaciones que sufren los datos entre sistemas?
E11: 3. ¿El linaje permite rastrear un error hasta su origen?
B13: Gestión centralizada de metadatos | C13: Los metadatos se gestionan en una herramienta o repositorio centralizado. | D13: 1 | E13: 1. ¿Los metadatos se gestionan en una herramienta centralizada (catálogo de datos)?
E14: 2. ¿Los metadatos se actualizan cuando cambia el modelo de datos o los procesos?
E15: 3. ¿Los metadatos son accesibles para los usuarios que los necesitan?
B18: Puntaje promedio del componente | D18: =IFERROR(AVERAGE(D5,D9,D13),"") -> 1

Sheet C8 – Analítica e inteligenc
B1: COMPONENTE 8 · ANALÍTICA E INTELIGENCIA DE DATOS
B2: Aprovecha los datos del proceso de venta para generar insights y apoyar la toma de decisiones.
B3: Escala: 1 No iniciado · 2 Conceptual · 3 En desarrollo · 4 Definido · 5 Logrado · 6 Mejorado
B4: Capacidad | C4: Descripción | D4: Puntaje (1–6) | E4: Preguntas de evidencia | F4: Evidencia observada (documentar hallazgo) | G4: Acción de mejora recomendada
B5: Reportes y dashboards operativos | C5: Existen reportes estandarizados que apoyan las operaciones diarias de la subasta. | D5: 4 | E5: 1. ¿Existen reportes estándar de resultados de subasta (precios, volumen, compradores)?
E6: 2. ¿Los reportes son confiables y los usuarios los usan para tomar decisiones?
E7: 3. ¿Los reportes están disponibles oportunamente después de cada evento de subasta?
B9: Análisis histórico y tendencias | C9: Se analiza la evolución de datos históricos para identificar patrones y tendencias. | D9: 2 | E9: 1. ¿Se analizan tendencias de precios de ganado a lo largo del tiempo?
E10: 2. ¿Se identifican patrones de comportamiento de compradores o vendedores recurrentes?
E11: 3. ¿Los análisis históricos se usan para mejorar la planificación de subastas?
B13: Gobierno del ciclo analítico | C13: El proceso de generación y publicación de análisis tiene controles y responsables. | D13: 3 | E13: 1. ¿Los reportes y análisis tienen un responsable definido de su calidad y actualización?
E14: 2. ¿Existe un proceso de validación antes de publicar análisis a la gerencia?
E15: 3. ¿Se documenta la fuente y metodología de los indicadores reportados?
B18: Puntaje promedio del componente | D18: =IFERROR(AVERAGE(D5,D9,D13),"") -> 3

Sheet Diagnóstico y Radar
B1: DIAGNÓSTICO CONSOLIDADO DE MADUREZ DCAM
B2: Los puntajes se actualizan automáticamente desde las hojas de cada componente
B4: Componente DCAM | C4: Puntaje Promedio | D4: Nivel de madurez | E4: Principales brechas identificadas | F4: Prioridad de mejora (A/M/B)
B5: C1 · Estrategia de gestión de datos | C5: =IFERROR('C1 – Estrategia de gestión '!D18,"") -> 4.3333333 | D5: =IFERROR(IF('C1 – Estrategia de gestión '!D18="","—",IF('C1 – Estrategia de gestión '!D18<1.5,"No iniciado",IF('C1 – Estrategia de gestión '!D18<2.5,"Conceptual",IF('C1 – Estrategia de gestión '!D18<3.5,"En desarrollo",IF('C1 – Estrategia de gestión '!D18<4.5,"Definido",IF('C1 – Estrategia de gestión '!D18<5.5,"Logrado","Mejorado")))))),"—") -> Definido | E5: la soluciones existentes permiten la gestion en sus diferentes etapas, es una solucion funcional en linea | F5: mejorar e innovar
B6: C2 · Programa y financiamiento | C6: =IFERROR('C2 – Programa y financiamie'!D18,"") -> 2.3333333 | D6: =IFERROR(IF('C2 – Programa y financiamie'!D18="","—",IF('C2 – Programa y financiamie'!D18<1.5,"No iniciado",IF('C2 – Programa y financiamie'!D18<2.5,"Conceptual",IF('C2 – Programa y financiamie'!D18<3.5,"En desarrollo",IF('C2 – Programa y financiamie'!D18<4.5,"Definido",IF('C2 – Programa y financiamie'!D18<5.5,"Logrado","Mejorado")))))),"—") -> Conceptual | E6: Las aplicicones pertenecen a terceros y y no existen integraciones , por lo que la comunincacion resulta ser un proceso manual, que introduce un posible error humnano
B7: C3 · Gobernanza de datos | C7: =IFERROR('C3 – Gobernanza de datos'!D22,"") -> 1.75 | D7: =IFERROR(IF('C3 – Gobernanza de datos'!D22="","—",IF('C3 – Gobernanza de datos'!D22<1.5,"No iniciado",IF('C3 – Gobernanza de datos'!D22<2.5,"Conceptual",IF('C3 – Gobernanza de datos'!D22<3.5,"En desarrollo",IF('C3 – Gobernanza de datos'!D22<4.5,"Definido",IF('C3 – Gobernanza de datos'!D22<5.5,"Logrado","Mejorado")))))),"—") -> Conceptual | E7: no fomra parte del prceoso de subastar Ecuador, la gestión y toma de deciciones
B8: C4 · Arquitectura de datos | C8: =IFERROR('C4 – Arquitectura de datos'!D18,"") -> 2 | D8: =IFERROR(IF('C4 – Arquitectura de datos'!D18="","—",IF('C4 – Arquitectura de datos'!D18<1.5,"No iniciado",IF('C4 – Arquitectura de datos'!D18<2.5,"Conceptual",IF('C4 – Arquitectura de datos'!D18<3.5,"En desarrollo",IF('C4 – Arquitectura de datos'!D18<4.5,"Definido",IF('C4 – Arquitectura de datos'!D18<5.5,"Logrado","Mejorado")))))),"—") -> Conceptual
B9: C5 · Calidad de datos | C9: =IFERROR('C5 – Calidad de datos'!D22,"") -> 2 | D9: =IFERROR(IF('C5 – Calidad de datos'!D22="","—",IF('C5 – Calidad de datos'!D22<1.5,"No iniciado",IF('C5 – Calidad de datos'!D22<2.5,"Conceptual",IF('C5 – Calidad de datos'!D22<3.5,"En desarrollo",IF('C5 – Calidad de datos'!D22<4.5,"Definido",IF('C5 – Calidad de datos'!D22<5.5,"Logrado","Mejorado")))))),"—") -> Conceptual
B10: C6 · Control y riesgo de datos | C10: =IFERROR('C6 – Control y riesgo de da'!D22,"") -> 1.25 | D10: =IFERROR(IF('C6 – Control y riesgo de da'!D22="","—",IF('C6 – Control y riesgo de da'!D22<1.5,"No iniciado",IF('C6 – Control y riesgo de da'!D22<2.5,"Conceptual",IF('C6 – Control y riesgo de da'!D22<3.5,"En desarrollo",IF('C6 – Control y riesgo de da'!D22<4.5,"Definido",IF('C6 – Control y riesgo de da'!D22<5.5,"Logrado","Mejorado")))))),"—") -> No iniciado
B11: C7 · Metadatos | C11: =IFERROR('C7 – Metadatos'!D18,"") -> 1 | D11: =IFERROR(IF('C7 – Metadatos'!D18="","—",IF('C7 – Metadatos'!D18<1.5,"No iniciado",IF('C7 – Metadatos'!D18<2.5,"Conceptual",IF('C7 – Metadatos'!D18<3.5,"En desarrollo",IF('C7 – Metadatos'!D18<4.5,"Definido",IF('C7 – Metadatos'!D18<5.5,"Logrado","Mejorado")))))),"—") -> No iniciado
B12: C8 · Analítica e inteligencia de datos | C12: =IFERROR('C8 – Analítica e inteligenc'!D18,"") -> 3 | D12: =IFERROR(IF('C8 – Analítica e inteligenc'!D18="","—",IF('C8 – Analítica e inteligenc'!D18<1.5,"No iniciado",IF('C8 – Analítica e inteligenc'!D18<2.5,"Conceptual",IF('C8 – Analítica e inteligenc'!D18<3.5,"En desarrollo",IF('C8 – Analítica e inteligenc'!D18<4.5,"Definido",IF('C8 – Analítica e inteligenc'!D18<5.5,"Logrado","Mejorado")))))),"—") -> En desarrollo
B14: PUNTAJE GLOBAL DE MADUREZ | D14: =IFERROR(AVERAGE(C5,C6,C7,C8,C9,C10,C11,C12),"") -> 2.2083333

Sheet Plan de Mejora
B1: PLAN DE MEJORA DE GOBERNANZA DE DATOS
B2: Completar una fila por acción de mejora identificada durante la evaluación DCAM
B4: Comp. | C4: Capacidad afectada | D4: Acción de mejora | E4: Responsable | F4: Prioridad (A/M/B) | G4: Plazo estimado | H4: Estado | I4: Fecha cierre
